prestools/__init__.py
prestools/bioinf.py
prestools/classes.py
prestools/cli.py
prestools/clustering.py
prestools/graph.py
prestools/misc.py
prestools/prestools.py
prestools/commands/__init__.py
prestools/commands/bioinf.py
prestools/commands/clustering.py
prestools/commands/graph.py
prestools/commands/misc.py
prestools-0.2.1.dist-info/AUTHORS.rst
prestools-0.2.1.dist-info/LICENSE
prestools-0.2.1.dist-info/METADATA
prestools-0.2.1.dist-info/WHEEL
prestools-0.2.1.dist-info/entry_points.txt
prestools-0.2.1.dist-info/top_level.txt
prestools-0.2.1.dist-info/RECORD
