Metadata-Version: 2.1
Name: prestools
Version: 0.2.1
Summary: My personal functions and utilities for Python programming.
Home-page: https://github.com/robertopreste/prestools
Author: Roberto Preste
Author-email: robertopreste@gmail.com
License: MIT license
Keywords: prestools
Platform: UNKNOWN
Classifier: Development Status :: 2 - Pre-Alpha
Classifier: Intended Audience :: Developers
Classifier: License :: OSI Approved :: MIT License
Classifier: Natural Language :: English
Classifier: Programming Language :: Python :: 3
Classifier: Programming Language :: Python :: 3.6
Classifier: Programming Language :: Python :: 3.7
Requires-Dist: Click
Requires-Dist: requests
Requires-Dist: scipy
Requires-Dist: pandas
Requires-Dist: numpy
Requires-Dist: matplotlib
Requires-Dist: seaborn
